mirai_translate/__init__.py
mirai_translate/lib.py
mirai_translate-0.1.3.dist-info/WHEEL
mirai_translate-0.1.3.dist-info/METADATA
mirai_translate-0.1.3.dist-info/RECORD
