Metadata-Version: 2.1
Name: mirai-translate
Version: 0.1.3
Summary: Unofficial Mirai Translate API for Python
Home-page: https://github.com/reiyw/mirai-translate
Author: reiyw
Author-email: reiyw.setuve@gmail.com
Requires-Python: >=3.7,<4.0
Classifier: Programming Language :: Python :: 3
Classifier: Programming Language :: Python :: 3.7
Classifier: Programming Language :: Python :: 3.8
Classifier: Programming Language :: Python :: 3.9
Requires-Dist: httpx (>=0.17.1,<0.18.0)
Project-URL: Repository, https://github.com/reiyw/mirai-translate
